QLog/__init__.py
QLog/azure_system_logger.py
QLog/console_logger.py
QLog/file_logger.py
QLog/log_entry.py
QLog/log_level.py
QLog/logger.py
QLog/main.py
QLog/system_logger.py
QLog-0.2.3.dist-info/METADATA
QLog-0.2.3.dist-info/WHEEL
QLog-0.2.3.dist-info/top_level.txt
QLog-0.2.3.dist-info/RECORD
