Metadata-Version: 2.1
Name: QLog
Version: 0.2.3
Summary: Logger
Home-page: https://github.com/QuantumApplications/QLog-Python
Author: Quantum Applications
Author-email: oberdoerfer@quantum.qa
License: MIT
Platform: UNKNOWN
Classifier: License :: OSI Approved :: MIT License
Classifier: Programming Language :: Python :: 3
Classifier: Programming Language :: Python :: 3.7
Classifier: Programming Language :: Python :: 3.8
